MANIFEST.in
VERSION
setup.py
aegisx.egg-info/PKG-INFO
aegisx.egg-info/SOURCES.txt
aegisx.egg-info/dependency_links.txt
aegisx.egg-info/requires.txt
aegisx.egg-info/top_level.txt
aegisx/core/__init__.py
aegisx/core/const.py
aegisx/core/package.json
aegisx/core/backend/__init__.py
aegisx/lib/__init__.py
aegisx/types/__init__.py
aegisx/types/_plainbase64.py